README.md
setup.py
hoomy/__init__.py
hoomy/dateutil.py
hoomy/help.py
hoomy/listutil.py
hoomy.egg-info/PKG-INFO
hoomy.egg-info/SOURCES.txt
hoomy.egg-info/dependency_links.txt
hoomy.egg-info/top_level.txt