Metadata-Version: 2.1
Name: hoomy
Version: 1.6.28
Summary: Development tools for python
Home-page: https://github.com/qicongsheng/hoomy
Author: qicongsheng
Author-email: qicongsheng@outlook.com
License: MIT License
Keywords: hoomy
Platform: any
